{
  "millisecond": "毫秒",
  "second": "第二",
  "minute": "钟",
  "hour": "小时",
  "day": "一天",
  "week": "周",
  "month": "一个月",
  "year": "年",
  "decade": "十年",
  "century": "世纪",
  "millennium": "千年",
  "milliseconds": "毫秒",
  "seconds": "几秒钟",
  "minutes": "分钟",
  "hours": "小时",
  "days": "天",
  "weeks": "星期",
  "months": "几个月",
  "years": "年",
  "decades": "几十年",
  "centuries": "几个世纪",
  "millennia": "几千年",
  "January": "一月",
  "February": "二月",
  "March": "三月",
  "April": "四月",
  "May": "可",
  "June": "六月",
  "July": "七月",
  "August": "八月",
  "September": "九月",
  "October": "十月",
  "November": "十一月",
  "December": "十二月",
  "Monday": "星期一",
  "Tuesday": "星期二",
  "Wednesday": "星期三",
  "Thursday": "星期四",
  "Friday": "星期五",
  "Saturday": "星期六",
  "Sunday": "周日"
}
